{
  "type": "Feature",
  "properties": {
    "iso:country":"HU",
    "sg:address":"Velencei \u00fat 37.",
    "sg:city":"\u00c9rd",
    "sg:classifiers":[
        {
            "category":"Manufacturing",
            "subcategory":"Electronics",
            "type":"Manufacturing & Wholesale Goods"
        }
    ],
    "sg:postcode":"H-2030",
    "sg:tags":[
        "mobile",
        "industrial",
        "gps",
        "gprs",
        "cellular",
        "zigbee",
        "silverlight",
        "ria",
        "data-collection",
        "fleet-management",
        "fleet",
        "perosnal-security",
        "security",
        "oil",
        "oil-industry",
        "gas",
        "energy",
        "electrical",
        "electrical-energy",
        "wireless",
        "research",
        "manufacturing",
        "pipeline",
        "cathod",
        "c"
    ],
    "sg:website":"http://www.casonplc.com",
    "wof:name":"CASON",
    "wof:placetype":"venue"
},
  "geometry": {"coordinates":[18.9082252,47.3752475],"type":"Point"}
}